stix_shifter/__init__.py
stix_shifter/scripts/__init__.py
stix_shifter/scripts/stix_shifter.py
stix_shifter/scripts/supported_property_exporter.py
stix_shifter/stix_translation/__init__.py
stix_shifter/stix_translation/json_to_stix_translator.py
stix_shifter/stix_translation/stix_translation.py
stix_shifter/stix_transmission/__init__.py
stix_shifter/stix_transmission/stix_transmission.py
stix_shifter-8.0.2.dist-info/licenses/AUTHORS.md
stix_shifter-8.0.2.dist-info/licenses/LICENSE.md
stix_shifter-8.0.2.dist-info/licenses/NOTICE
stix_shifter-8.0.2.dist-info/METADATA
stix_shifter-8.0.2.dist-info/WHEEL
stix_shifter-8.0.2.dist-info/entry_points.txt
stix_shifter-8.0.2.dist-info/top_level.txt
stix_shifter-8.0.2.dist-info/RECORD
