Metadata-Version: 2.4
Name: stix_shifter
Version: 8.0.2
Summary: Tools and interface to translate STIX formatted results and queries to different data source formats and to set up appropriate connection strings for invoking and triggering actions in openwhisk
Author: ibm
License-Expression: Apache-2.0
Project-URL: Homepage, https://github.com/opencybersecurityalliance/stix-shifter
Project-URL: Source, https://github.com/opencybersecurityalliance/stix-shifter
Keywords: datasource,stix,translate,transform,transmit
Classifier: Programming Language :: Python :: 3.10
Classifier: Programming Language :: Python :: 3.11
Classifier: Programming Language :: Python :: 3.12
Requires-Python: >=3.10
License-File: LICENSE.md
License-File: AUTHORS.md
License-File: NOTICE
Requires-Dist: aioboto3==15.0.0
Requires-Dist: aiohttp-retry==2.8.3
Requires-Dist: aiomysql==0.2.0
Requires-Dist: antlr4-python3-runtime==4.8
Requires-Dist: asyncio==3.4.3
Requires-Dist: asynctest==0.13.0
Requires-Dist: attrs==23.1.0
Requires-Dist: azure-identity==1.19.0
Requires-Dist: colorlog==6.8.2
Requires-Dist: flask==3.0.0
Requires-Dist: flatten_json==0.1.14
Requires-Dist: json-fix==1.0.0
Requires-Dist: jsonmerge==1.9.2
Requires-Dist: numpy<1.27,>=1.26
Requires-Dist: pyOpenSSL==25.0.0
Requires-Dist: python-dateutil<3.0.0,>=2.9.0
Requires-Dist: regex==2023.12.25
Requires-Dist: stix2-matcher==3.0.0
Requires-Dist: stix2-patterns==1.3.2
Requires-Dist: urllib3<3.0.0,>=2.5.0
Requires-Dist: xmltodict==0.13.0
Dynamic: license-file
